stuf/__init__.py
stuf/_core.py
stuf/base.py
stuf/collects.py
stuf/core.py
stuf/deep.py
stuf/desc.py
stuf/iterable.py
stuf/patterns.py
stuf/six.py
stuf/utils.py
stuf/xreload.py
stuf-0.9.16.dist-info/DESCRIPTION.rst
stuf-0.9.16.dist-info/METADATA
stuf-0.9.16.dist-info/RECORD
stuf-0.9.16.dist-info/WHEEL
stuf-0.9.16.dist-info/metadata.json
stuf-0.9.16.dist-info/top_level.txt
tests/__init__.py
tests/test_stuf.py
tests/test_utils.py
